{
    "backend": "flask",
    "db_name": "",
    "db_pass": "",
    "db_type": "mysql",
    "db_user": "",
    "dbms": "1",
    "description": "generated product",
    "design": "soft-ui-dashboard",
    "docker": "0",
    "err_code": 0,
    "frontend": "",
    "heroku": "0",
    "pattern": "mvc",
    "pro": "0",
    "task_id": "31593219-b03b-48f1-b85a-9f562f4f4e97",
    "task_info": "Upload Sources [0%] - 330 files",
    "task_output": "31593219-b03b-48f1-b85a-9f562f4f4e97.zip",
    "task_result": "SUCCESS",
    "task_state": "RUNNING",
    "task_ts_end": "2023-08-26-02-51-00",
    "task_ts_start": "2023-08-26-02-50-57"
}